exonote/__init__.py
exonote/__main__.py
exonote/constant/__init__.py
exonote/dto/__init__.py
exonote/editor/__init__.py
exonote/element/__init__.py
exonote/error/__init__.py
exonote/inserter/__init__.py
exonote/inserter/attachment.py
exonote/inserter/codeblock.py
exonote/inserter/heading.py
exonote/inserter/link.py
exonote/inserter/program.py
exonote/inserter/table.py
exonote/inserter/util.py
exonote/parser/__init__.py
exonote/pattern/__init__.py
exonote/scanner/__init__.py
exonote/statusbar/__init__.py
exonote/style/__init__.py
exonote/utils/__init__.py
exonote/viewer/__init__.py
exonote/viewer/util.py
tests/__init__.py
tests/util.py
tests/parser/__init__.py
tests/parser/test_attachment_element.py
tests/parser/test_bold_element.py
tests/parser/test_code_element.py
tests/parser/test_codeblock_element.py
tests/parser/test_heading_element.py
tests/parser/test_italic_element.py
tests/parser/test_link_element.py
tests/parser/test_metablock_element.py
tests/parser/test_monospace_element.py
tests/parser/test_notice_element.py
tests/parser/test_program_element.py
tests/parser/test_strikethrough_element.py
tests/parser/test_underline_element.py
tests/parser/test_warning_element.py
exonote-0.0.5.dist-info/LICENSE
exonote-0.0.5.dist-info/METADATA
exonote-0.0.5.dist-info/WHEEL
exonote-0.0.5.dist-info/entry_points.txt
exonote-0.0.5.dist-info/top_level.txt
exonote-0.0.5.dist-info/RECORD
