Metadata-Version: 2.1
Name: exonote
Version: 0.0.5
Summary: Write and render rich, scriptable, and interactive notes
Home-page: https://github.com/pyrustic/exonote
Author: Pyrustic Evangelist
Author-email: rusticalex@yahoo.com
Maintainer: Pyrustic Evangelist
Maintainer-email: rusticalex@yahoo.com
License: MIT
Keywords: library,note,markdown,exonote,exn,GUI,render,application,pyrustic
Platform: UNKNOWN
Classifier: Programming Language :: Python :: 3
Classifier: License :: OSI Approved :: MIT License
Classifier: Operating System :: OS Independent
Requires-Python: >=3.5
License-File: LICENSE
Requires-Dist: oscan
Requires-Dist: tkutil
